AO3Parser/__init__.py
AO3Parser/extra.py
AO3Parser/page.py
AO3Parser/params.py
AO3Parser/search.py
AO3Parser/work.py
ao3_parser-3.1.1.dist-info/licenses/LICENSE
ao3_parser-3.1.1.dist-info/METADATA
ao3_parser-3.1.1.dist-info/WHEEL
ao3_parser-3.1.1.dist-info/top_level.txt
ao3_parser-3.1.1.dist-info/RECORD
