Metadata-Version: 2.4
Name: ao3-parser
Version: 3.1.1
Summary: Package for parsing AO3 pages into works and creating urls based on requirements.
Author: petak33
License: MIT License
Project-URL: Homepage, https://github.com/petak33/ao3-parser
Project-URL: Issues, https://github.com/petak33/ao3-parser/issues
Keywords: ao3,archiveofourown,archive of our own,ao3 api
Classifier: Programming Language :: Python :: 3
Classifier: License :: OSI Approved :: MIT License
Classifier: Operating System :: OS Independent
Requires-Python: >=3.8
License-File: LICENSE
Requires-Dist: BeautifulSoup4
Dynamic: license-file
